archivy/__init__.py
archivy/api.py
archivy/cli.py
archivy/config.py
archivy/data.py
archivy/forms.py
archivy/helpers.py
archivy/models.py
archivy/routes.py
archivy/search.py
archivy/tags.py
archivy/click_web/__init__.py
archivy/click_web/exceptions.py
archivy/click_web/web_click_types.py
archivy/click_web/resources/__init__.py
archivy/click_web/resources/cmd_exec.py
archivy/click_web/resources/cmd_form.py
archivy/click_web/resources/index.py
archivy/click_web/resources/input_fields.py
archivy/static/HIGHLIGHTJS-LICENSE
archivy/static/accessibility.css
archivy/static/archivy.svg
archivy/static/delete.png
archivy/static/editor.css
archivy/static/editor.js
archivy/static/editor_dark.css
archivy/static/highlight.js
archivy/static/logo.png
archivy/static/main.css
archivy/static/main_dark.css
archivy/static/markdown.css
archivy/static/markdown_dark.css
archivy/static/math.css
archivy/static/math.js
archivy/static/monokai.css
archivy/static/mvp.css
archivy/static/open_form.js
archivy/static/parser.js
archivy/static/post_and_read.js
archivy/static/profile.svg
archivy/templates/base.html
archivy/templates/bookmarklet.html
archivy/templates/config.html
archivy/templates/home.html
archivy/templates/markdown-parser.html
archivy/templates/click_web/command_form.html
archivy/templates/click_web/form_macros.html
archivy/templates/click_web/show_tree.html
archivy/templates/dataobjs/new.html
archivy/templates/dataobjs/show.html
archivy/templates/tags/all.html
archivy/templates/tags/show.html
archivy/templates/users/edit.html
archivy/templates/users/login.html
tests/__init__.py
tests/test_click_web.py
tests/test_request_parsing.py
archivy-1.7.7.dist-info/LICENSE
archivy-1.7.7.dist-info/METADATA
archivy-1.7.7.dist-info/WHEEL
archivy-1.7.7.dist-info/entry_points.txt
archivy-1.7.7.dist-info/top_level.txt
archivy-1.7.7.dist-info/RECORD
