Metadata-Version: 2.1
Name: archivy
Version: 1.7.7
Summary: Minimalist knowledge base focused on digital preservation and building your second brain.
Home-page: https://github.com/archivy/archivy
Author: Uzay-G
Author-email: halcyon@disroot.org
Classifier: Programming Language :: Python :: 3
Classifier: License :: OSI Approved :: MIT License
Requires-Python: >=3.6
License-File: LICENSE
Requires-Dist: Flask (==2.3.2)
Requires-Dist: werkzeug (==2.3.3)
Requires-Dist: jinja2 (==3.1.2)
Requires-Dist: Flask-WTF (==1.1.1)
Requires-Dist: WTForms (==2.3.1)
Requires-Dist: appdirs (==1.4.4)
Requires-Dist: attrs (==20.2.0)
Requires-Dist: beautifulsoup4 (>=4.8.2)
Requires-Dist: elasticsearch (==7.7.1)
Requires-Dist: python-dotenv (==0.13.0)
Requires-Dist: python-frontmatter (==0.5.0)
Requires-Dist: requests (==2.30.0)
Requires-Dist: tinydb (==4.1.1)
Requires-Dist: validators (==0.15.0)
Requires-Dist: flask-login (==0.6.2)
Requires-Dist: click-plugins
Requires-Dist: html2text
Requires-Dist: flask-compress
Requires-Dist: readability-lxml
